retrace.py
retrace-3.0.0.dist-info/AUTHORS
retrace-3.0.0.dist-info/LICENSE
retrace-3.0.0.dist-info/METADATA
retrace-3.0.0.dist-info/WHEEL
retrace-3.0.0.dist-info/pbr.json
retrace-3.0.0.dist-info/top_level.txt
retrace-3.0.0.dist-info/RECORD
