Metadata-Version: 2.1
Name: retrace
Version: 3.0.0
Summary: Configurable elegant retrying.
Home-page: https://github.com/d0ugal/retrace
Author: Dougal Matthews
Author-email: dougal@dougalmatthews.com
License: BSD
Keywords: decorator,retry,retrying,exception,exponential,backoff
Platform: UNKNOWN
Classifier: Intended Audience :: Developers
Classifier: Natural Language :: English
Classifier: License :: OSI Approved :: Apache Software License
Classifier: Programming Language :: Python
Classifier: Programming Language :: Python :: 3.3
Classifier: Programming Language :: Python :: 3.4
Classifier: Programming Language :: Python :: 3.5
Classifier: Programming Language :: Python :: 3.6
Classifier: Programming Language :: Python :: 3.7
Classifier: Topic :: Internet
Classifier: Topic :: Utilities
